odoo/addons/sale_line_returned_qty/README.rst
odoo/addons/sale_line_returned_qty/__init__.py
odoo/addons/sale_line_returned_qty/__manifest__.py
odoo/addons/sale_line_returned_qty/i18n/es.po
odoo/addons/sale_line_returned_qty/i18n/it.po
odoo/addons/sale_line_returned_qty/i18n/sale_line_returned_qty.pot
odoo/addons/sale_line_returned_qty/models/__init__.py
odoo/addons/sale_line_returned_qty/models/sale_order_line.py
odoo/addons/sale_line_returned_qty/readme/CONTRIBUTORS.md
odoo/addons/sale_line_returned_qty/readme/DESCRIPTION.md
odoo/addons/sale_line_returned_qty/static/description/icon.png
odoo/addons/sale_line_returned_qty/static/description/index.html
odoo/addons/sale_line_returned_qty/tests/__init__.py
odoo/addons/sale_line_returned_qty/tests/test_sale_line_returned_qty.py
odoo/addons/sale_line_returned_qty/views/sale_order_views.xml
odoo_addon_sale_line_returned_qty-18.0.1.0.0.2.dist-info/METADATA
odoo_addon_sale_line_returned_qty-18.0.1.0.0.2.dist-info/WHEEL
odoo_addon_sale_line_returned_qty-18.0.1.0.0.2.dist-info/top_level.txt
odoo_addon_sale_line_returned_qty-18.0.1.0.0.2.dist-info/RECORD
